LICENSE
MANIFEST.in
README.md
setup.py
quiz_app/__init__.py
quiz_app/main.py
quiz_app/questions.json
quiz_app/quiz.py
sasuke_quiz.egg-info/PKG-INFO
sasuke_quiz.egg-info/SOURCES.txt
sasuke_quiz.egg-info/dependency_links.txt
sasuke_quiz.egg-info/entry_points.txt
sasuke_quiz.egg-info/top_level.txt
tests/__init__.py
tests/test_quiz.py