Metadata-Version: 2.1
Name: sasuke_quiz
Version: 0.1.0
Summary: sasukeに関する簡単な問題を作りました
Home-page: https://github.com/nousouhiroyuki/quiz_app
Author: sasukekun
Author-email: s2222070@stu.musashino-u.ac.jp
Classifier: Programming Language :: Python :: 3
Classifier: License :: OSI Approved :: MIT License
Classifier: Operating System :: OS Independent
Requires-Python: >=3.6
